ragpdf/__init__.py
ragpdf/embedding_manager.py
ragpdf/models.py
ragpdf/pdf_processor.py
ragpdf/query_manager.py
ragpdf/ragpdf.py
ragpdf-0.1.2.dist-info/METADATA
ragpdf-0.1.2.dist-info/WHEEL
ragpdf-0.1.2.dist-info/top_level.txt
ragpdf-0.1.2.dist-info/RECORD
