Metadata-Version: 2.2
Name: ragpdf
Version: 0.1.2
Summary: Retrive PDF files context for your LLMs
Home-page: https://github.com/alfredwallace7/ragpdf
Author: Alfred Wallace
Author-email: alfred.wallace@netcraft.fr
Project-URL: Bug Reports, https://github.com/alfredwallace7/ragpdf/issues
Project-URL: Source, https://github.com/alfredwallace7/ragpdf
Keywords: rag pdf llm embeddings vector-search faiss context retrieval augmented generation
Classifier: Development Status :: 3 - Alpha
Classifier: Intended Audience :: Developers
Classifier: License :: OSI Approved :: MIT License
Classifier: Operating System :: OS Independent
Classifier: Programming Language :: Python :: 3
Classifier: Programming Language :: Python :: 3.8
Classifier: Programming Language :: Python :: 3.9
Classifier: Programming Language :: Python :: 3.10
Classifier: Programming Language :: Python :: 3.11
Classifier: Programming Language :: Python :: 3.12
Classifier: Topic :: Software Development :: Libraries :: Python Modules
Classifier: Topic :: Text Processing :: General
Requires-Python: >=3.8
Requires-Dist: litellm>=1.30.3
Requires-Dist: faiss-cpu>=1.7.4
Requires-Dist: PyPDF2>=3.0.0
Requires-Dist: numpy>=1.24.0
Requires-Dist: pydantic>=2.5.0
Requires-Dist: python-dotenv>=1.0.0
Dynamic: author
Dynamic: author-email
Dynamic: classifier
Dynamic: description
Dynamic: description-content-type
Dynamic: home-page
Dynamic: keywords
Dynamic: project-url
Dynamic: requires-dist
Dynamic: requires-python
Dynamic: summary
